odoo/addons/mail_print/README.rst
odoo/addons/mail_print/__init__.py
odoo/addons/mail_print/__manifest__.py
odoo/addons/mail_print/data/report_paperformat_data.xml
odoo/addons/mail_print/i18n/es.po
odoo/addons/mail_print/i18n/it.po
odoo/addons/mail_print/i18n/mail_print.pot
odoo/addons/mail_print/readme/DESCRIPTION.md
odoo/addons/mail_print/readme/USAGE.md
odoo/addons/mail_print/reports/report_mail_message.xml
odoo/addons/mail_print/reports/reports.xml
odoo/addons/mail_print/static/description/icon.png
odoo/addons/mail_print/static/description/index.html
odoo/addons/mail_print/static/src/components/print_message/print_message.esm.js
odoo/addons/mail_print/static/src/components/print_message/print_message.xml
odoo/addons/mail_print/static/src/core/common/message_actions.esm.js
odoo/addons/mail_print/static/tests/tours/mail_print.esm.js
odoo/addons/mail_print/tests/__init__.py
odoo/addons/mail_print/tests/test_mail_print.py
odoo_addon_mail_print-17.0.1.0.0.5.dist-info/METADATA
odoo_addon_mail_print-17.0.1.0.0.5.dist-info/WHEEL
odoo_addon_mail_print-17.0.1.0.0.5.dist-info/top_level.txt
odoo_addon_mail_print-17.0.1.0.0.5.dist-info/RECORD
